{
  "auth": {
    "boyaki39c7f4de": {
      "service": "Cognito",
      "providerPlugin": "awscloudformation",
      "dependsOn": [],
      "customAuth": false
    }
  },
  "api": {
    "BoyakiGql": {
      "service": "AppSync",
      "providerPlugin": "awscloudformation",
      "output": {
        "authConfig": {
          "defaultAuthentication": {
            "authenticationType": "AMAZON_COGNITO_USER_POOLS",
            "userPoolConfig": {
              "userPoolId": "authboyaki39c7f4de"
            }
          },
          "additionalAuthenticationProviders": [
            {
              "authenticationType": "AWS_IAM"
            }
          ]
        }
      }
    }
  },
  "hosting": {
    "amplifyhosting": {
      "service": "amplifyhosting",
      "providerPlugin": "awscloudformation",
      "type": "manual"
    }
  },
  "function": {}
}